nepaldatascrapper/NRB.py
nepaldatascrapper/__init__.py
nepaldatascrapper/__main__.py
nepaldatascrapper/nepalipaisa.py
nepaldatascrapper/nepalstock.py
nepaldatascrapper/scrapper.py
nepaldatascrapper-0.0.5.1.dist-info/LICENSE
nepaldatascrapper-0.0.5.1.dist-info/METADATA
nepaldatascrapper-0.0.5.1.dist-info/WHEEL
nepaldatascrapper-0.0.5.1.dist-info/top_level.txt
nepaldatascrapper-0.0.5.1.dist-info/RECORD
