Metadata-Version: 2.1
Name: nepaldatascrapper
Version: 0.0.5.1
Summary: Package that scraps data related to Nepal for further analysis through panda or spreadsheet.
Home-page: https://github.com/shubhajeet/nepaldatascrapper
Author: Sujit Maharjan
Author-email: shubhajeet.per@gmail.com
License: UNKNOWN
Platform: UNKNOWN
Classifier: Programming Language :: Python :: 3
Classifier: Operating System :: OS Independent
Requires-Python: >=3.6
